matchviz/__about__.py
matchviz/__init__.py
matchviz/annotation.py
matchviz/bigstitcher.py
matchviz/cli.py
matchviz/core.py
matchviz/neuroglancer_styles.py
matchviz/plot.py
matchviz/py.typed
matchviz/schemas.py
matchviz/transform.py
matchviz/types.py
matchviz-0.0.13.dist-info/METADATA
matchviz-0.0.13.dist-info/WHEEL
matchviz-0.0.13.dist-info/entry_points.txt
matchviz-0.0.13.dist-info/licenses/LICENSE.txt
matchviz-0.0.13.dist-info/RECORD
