Metadata-Version: 2.3
Name: matchviz
Version: 0.0.13
Project-URL: Documentation, https://github.com/unknown/matchviz#readme
Project-URL: Issues, https://github.com/unknown/matchviz/issues
Project-URL: Source, https://github.com/unknown/matchviz
Author-email: Davis Vann Bennett <davis.v.bennett@gmail.com>
License-Expression: MIT
License-File: LICENSE.txt
Classifier: Development Status :: 4 - Beta
Classifier: Programming Language :: Python
Classifier: Programming Language :: Python :: 3.10
Classifier: Programming Language :: Python :: 3.11
Classifier: Programming Language :: Python :: 3.12
Classifier: Programming Language :: Python :: Implementation :: CPython
Classifier: Programming Language :: Python :: Implementation :: PyPy
Requires-Python: >=3.10
Requires-Dist: click==8.1.7
Requires-Dist: fsspec[s3]==2024.3.1
Requires-Dist: matplotlib
Requires-Dist: neuroglancer==2.39.2
Requires-Dist: polars>=1.0
Requires-Dist: pydantic-bigstitcher>=0.0.10
Requires-Dist: pydantic-zarr==0.7.0
Requires-Dist: structlog<25,>=24.4.0
Requires-Dist: tensorstore==0.1.62
Requires-Dist: tqdm==4.66.4
Requires-Dist: xarray-ome-ngff<4,>=3.1.1
Requires-Dist: zarr==2.18
